pdf_tools_service/__init__.py
pdf_tools_service/config.py
pdf_tools_service/server.py
pdf_tools_service/storage.py
pdf_tools_service/utils.py
pdf2urls_tools_service-0.1.2.dist-info/METADATA
pdf2urls_tools_service-0.1.2.dist-info/WHEEL
pdf2urls_tools_service-0.1.2.dist-info/entry_points.txt
pdf2urls_tools_service-0.1.2.dist-info/top_level.txt
pdf2urls_tools_service-0.1.2.dist-info/RECORD
