Metadata-Version: 2.4
Name: pdf2urls-tools-service
Version: 0.1.2
Summary: Convert each page of PDF into an image, output base64 encoding, and support uploading to Tencent Cloud OSS to obtain URL
Requires-Python: >=3.12
Requires-Dist: mcp[cli]>=1.12.4
Requires-Dist: pillow>=11.3.0
Requires-Dist: pymupdf>=1.26.3
Requires-Dist: requests>=2.32.4
Requires-Dist: cos-python-sdk-v5>=1.9.38
